needful/__init__.py
needful/_css.py
needful/_presentation.py
needful/_preview.py
needful/_slide.py
needful/_slide_mixins/__init__.py
needful/_slide_mixins/_bokeh_figure.py
needful/_slide_mixins/_mpl_figure.py
needful/_slide_mixins/_plotly_figure.py
needful/_slide_mixins/grid_object.py
needful/_slide_mixins/images.py
needful/_slide_mixins/mixin.py
needful/_slide_mixins/plots.py
needful/_slide_mixins/textboxes.py
needful/_utils/__init__.py
needful/static/default.css
needful/static/load-bearing.css
needful/static/needful.js
needful/static/template.html
needful-0.6a1.dist-info/LICENSE
needful-0.6a1.dist-info/METADATA
needful-0.6a1.dist-info/WHEEL
needful-0.6a1.dist-info/top_level.txt
needful-0.6a1.dist-info/RECORD
