Metadata-Version: 2.1
Name: needful
Version: 0.6a1
Summary: needful - simple, lightweight, interactive HTML presentations and dashboards for data scientists
Home-page: https://github.com/jhdarcy/needful
Author: Jordan D'Arcy
Author-email: needful.py@gmail.com
License: UNKNOWN
Platform: UNKNOWN
Classifier: Programming Language :: Python :: 3
Classifier: License :: OSI Approved :: MIT License
Classifier: Operating System :: OS Independent
Requires-Python: >=3.6
